lionagi_qe/__init__.py
lionagi_qe/agents/__init__.py
lionagi_qe/agents/api_contract_validator.py
lionagi_qe/agents/chaos_engineer.py
lionagi_qe/agents/code_complexity.py
lionagi_qe/agents/coverage_analyzer.py
lionagi_qe/agents/deployment_readiness.py
lionagi_qe/agents/flaky_test_hunter.py
lionagi_qe/agents/fleet_commander.py
lionagi_qe/agents/performance_tester.py
lionagi_qe/agents/production_intelligence.py
lionagi_qe/agents/quality_analyzer.py
lionagi_qe/agents/quality_gate.py
lionagi_qe/agents/regression_risk_analyzer.py
lionagi_qe/agents/requirements_validator.py
lionagi_qe/agents/security_scanner.py
lionagi_qe/agents/test_data_architect.py
lionagi_qe/agents/test_executor.py
lionagi_qe/agents/test_generator.py
lionagi_qe/agents/visual_tester.py
lionagi_qe/api/__init__.py
lionagi_qe/api/auth.py
lionagi_qe/api/models.py
lionagi_qe/api/rate_limit.py
lionagi_qe/api/server.py
lionagi_qe/api/endpoints/__init__.py
lionagi_qe/api/endpoints/coverage.py
lionagi_qe/api/endpoints/fleet.py
lionagi_qe/api/endpoints/jobs.py
lionagi_qe/api/endpoints/performance.py
lionagi_qe/api/endpoints/quality.py
lionagi_qe/api/endpoints/security.py
lionagi_qe/api/endpoints/test.py
lionagi_qe/api/sdk/__init__.py
lionagi_qe/api/sdk/client.py
lionagi_qe/api/sdk/exceptions.py
lionagi_qe/api/workers/__init__.py
lionagi_qe/api/workers/tasks.py
lionagi_qe/badges/__init__.py
lionagi_qe/badges/api.py
lionagi_qe/badges/cache.py
lionagi_qe/badges/cli.py
lionagi_qe/badges/colors.py
lionagi_qe/badges/generator.py
lionagi_qe/badges/templates/base.svg.j2
lionagi_qe/badges/templates/flat-square.svg.j2
lionagi_qe/cli/__init__.py
lionagi_qe/cli/base.py
lionagi_qe/cli/ci_mode.py
lionagi_qe/cli/examples.py
lionagi_qe/cli/output.py
lionagi_qe/config/__init__.py
lionagi_qe/config/storage_config.py
lionagi_qe/core/base_agent.py
lionagi_qe/core/fleet.py
lionagi_qe/core/hooks.py
lionagi_qe/core/memory.py
lionagi_qe/core/orchestrator.py
lionagi_qe/core/orchestrator_wip.py
lionagi_qe/core/router.py
lionagi_qe_fleet-1.3.1.dist-info/METADATA
lionagi_qe_fleet-1.3.1.dist-info/WHEEL
lionagi_qe_fleet-1.3.1.dist-info/licenses/LICENSE
lionagi_qe_fleet-1.3.1.dist-info/RECORD
