Metadata-Version: 2.4
Name: lionagi-qe-fleet
Version: 1.3.1
Summary: Agentic Quality Engineering Fleet powered by LionAGI - 18 specialized AI agents for comprehensive software testing and quality assurance with CI/CD integration
Project-URL: Homepage, https://github.com/lionagi/lionagi-qe-fleet
Project-URL: Documentation, https://github.com/lionagi/lionagi-qe-fleet/tree/main/docs
Project-URL: Repository, https://github.com/lionagi/lionagi-qe-fleet
Project-URL: Issues, https://github.com/lionagi/lionagi-qe-fleet/issues
Project-URL: Changelog, https://github.com/lionagi/lionagi-qe-fleet/blob/main/CHANGELOG.md
Project-URL: Source Code, https://github.com/lionagi/lionagi-qe-fleet
Author: LionAGI QE Fleet Contributors
License: MIT
License-File: LICENSE
Keywords: agentic-testing,ai-agents,coverage-analysis,lionagi,qa,quality-assurance,quality-engineering,test-automation,test-generation,testing
Classifier: Development Status :: 5 - Production/Stable
Classifier: Intended Audience :: Developers
Classifier: License :: OSI Approved :: MIT License
Classifier: Operating System :: OS Independent
Classifier: Programming Language :: Python :: 3
Classifier: Programming Language :: Python :: 3.10
Classifier: Programming Language :: Python :: 3.11
Classifier: Programming Language :: Python :: 3.12
Classifier: Topic :: Scientific/Engineering :: Artificial Intelligence
Classifier: Topic :: Software Development :: Quality Assurance
Classifier: Topic :: Software Development :: Testing
Classifier: Typing :: Typed
Requires-Python: >=3.10
Requires-Dist: aiohttp>=3.9.0
Requires-Dist: asyncpg>=0.29.0
Requires-Dist: bandit>=1.7.0
Requires-Dist: coverage>=7.0.0
Requires-Dist: fastapi>=0.109.0
Requires-Dist: hypothesis>=6.100.0
Requires-Dist: lionagi>=0.18.2
Requires-Dist: pydantic>=2.8.0
Requires-Dist: pytest-asyncio>=1.1.0
Requires-Dist: pytest-cov>=6.0.0
Requires-Dist: pytest>=8.0.0
Requires-Dist: python-dotenv>=1.0.0
Requires-Dist: python-jose[cryptography]>=3.3.0
Requires-Dist: safety>=3.0.0
Requires-Dist: uvicorn>=0.27.0
Requires-Dist: websockets>=12.0
Provides-Extra: all
Requires-Dist: black>=24.0.0; extra == 'all'
Requires-Dist: fastapi>=0.109.0; extra == 'all'
Requires-Dist: fastmcp>=0.1.0; extra == 'all'
Requires-Dist: ipykernel>=6.29.0; extra == 'all'
Requires-Dist: ipython>=8.20.0; extra == 'all'
Requires-Dist: locust>=2.20.0; extra == 'all'
Requires-Dist: mcp>=0.1.0; extra == 'all'
Requires-Dist: mypy>=1.9.0; extra == 'all'
Requires-Dist: py-spy>=0.3.14; extra == 'all'
Requires-Dist: pytest-mock>=3.12.0; extra == 'all'
Requires-Dist: python-jose[cryptography]>=3.3.0; extra == 'all'
Requires-Dist: redis>=5.0.0; extra == 'all'
Requires-Dist: ruff>=0.3.0; extra == 'all'
Requires-Dist: uvicorn[standard]>=0.27.0; extra == 'all'
Requires-Dist: websockets>=12.0; extra == 'all'
Provides-Extra: api
Requires-Dist: fastapi>=0.109.0; extra == 'api'
Requires-Dist: python-jose[cryptography]>=3.3.0; extra == 'api'
Requires-Dist: uvicorn[standard]>=0.27.0; extra == 'api'
Requires-Dist: websockets>=12.0; extra == 'api'
Provides-Extra: dev
Requires-Dist: black>=24.0.0; extra == 'dev'
Requires-Dist: ipykernel>=6.29.0; extra == 'dev'
Requires-Dist: ipython>=8.20.0; extra == 'dev'
Requires-Dist: mypy>=1.9.0; extra == 'dev'
Requires-Dist: pytest-mock>=3.12.0; extra == 'dev'
Requires-Dist: ruff>=0.3.0; extra == 'dev'
Provides-Extra: mcp
Requires-Dist: fastmcp>=0.1.0; extra == 'mcp'
Requires-Dist: mcp>=0.1.0; extra == 'mcp'
Provides-Extra: performance
Requires-Dist: locust>=2.20.0; extra == 'performance'
Requires-Dist: py-spy>=0.3.14; extra == 'performance'
Provides-Extra: persistence
Requires-Dist: redis>=5.0.0; extra == 'persistence'
